program1_avishek18/__init__.py
program1_avishek18/code.py
program1_avishek18-0.0.4.dist-info/LICENSE
program1_avishek18-0.0.4.dist-info/METADATA
program1_avishek18-0.0.4.dist-info/WHEEL
program1_avishek18-0.0.4.dist-info/top_level.txt
program1_avishek18-0.0.4.dist-info/RECORD
