Metadata-Version: 2.1
Name: program1_avishek18
Version: 0.0.4
Summary: Sample Vulnerable code
Author-email: Example Author <author@example.com>
Project-URL: Homepage, https://github.com/pypa/sampleproject
Project-URL: Issues, https://github.com/pypa/sampleproject/issues
Classifier: Programming Language :: Python :: 3
Classifier: License :: OSI Approved :: MIT License
Classifier: Operating System :: OS Independent
Requires-Python: >=3.8
License-File: LICENSE
